README.rst
setup.py
cw_msgpack_coder/__init__.py
cw_msgpack_coder/umsgpack_coder.py
cw_msgpack_coder.egg-info/PKG-INFO
cw_msgpack_coder.egg-info/SOURCES.txt
cw_msgpack_coder.egg-info/dependency_links.txt
cw_msgpack_coder.egg-info/requires.txt
cw_msgpack_coder.egg-info/top_level.txt