Metadata-Version: 1.1
Name: cw-msgpack-coder
Version: 1.1.4
Summary: Simple and fast Python any object serialization with use msgpack.
Home-page: https://github.com/ChameleonRed/cw_msgpack_coder
Author: Cezary K. Wagner
Author-email: Cezary.Wagner@gmail.com
License: MIT
Keywords: msgpack serialization streaming object encoding decoding
Platform: UNKNOWN
Classifier: Development Status :: 5 - Production/Stable
Classifier: License :: OSI Approved :: MIT License
Classifier: Programming Language :: Python :: 3.6
Classifier: Topic :: Software Development
Classifier: Topic :: Software Development :: Libraries
Classifier: Topic :: Software Development :: Libraries :: Python Modules
